aerodash_v1/__init__.py
aerodash_v1/cli.py
aerodash_v1-1.4.dist-info/METADATA
aerodash_v1-1.4.dist-info/WHEEL
aerodash_v1-1.4.dist-info/entry_points.txt
aerodash_v1-1.4.dist-info/top_level.txt
aerodash_v1-1.4.dist-info/RECORD
