Metadata-Version: 2.1
Name: aerodash-v1
Version: 1.4
Author: Lokeshwaran Venugopal Balamurugan
Author-email: lokesh2000.balamurugan@gmail.com
Classifier: Programming Language :: Python :: 3
Classifier: License :: OSI Approved :: MIT License
Classifier: Operating System :: OS Independent
Requires-Dist: numpy
Requires-Dist: pandas
Requires-Dist: typer
Requires-Dist: requests
